README.md
setup.py
abei/__init__.py
abei.egg-info/PKG-INFO
abei.egg-info/SOURCES.txt
abei.egg-info/dependency_links.txt
abei.egg-info/top_level.txt
abei/implements/__init__.py
abei/implements/cache_redis.py
abei/implements/procedure_basic.py
abei/implements/procedure_builder.py
abei/implements/procedure_data_basic.py
abei/implements/procedure_joint_basic.py
abei/implements/procedure_site_basic.py
abei/implements/service.py
abei/implements/service_basic.py
abei/implements/service_redis.py
abei/implements/service_sqlalchemy.py
abei/implements/storage_argv.py
abei/implements/storage_composite.py
abei/implements/storage_ini_file.py
abei/implements/storage_memory.py
abei/implements/storage_yml_file.py
abei/implements/util.py
abei/interfaces/__init__.py
abei/interfaces/cache.py
abei/interfaces/service.py
abei/interfaces/storage.py
abei/interfaces/procedure/__init__.py
abei/interfaces/procedure/base.py
abei/interfaces/procedure/builder.py
abei/interfaces/procedure/data.py
abei/interfaces/procedure/joint.py
abei/interfaces/procedure/site.py